[
  {
    "rank": 1,
    "symbol": "BTC",
    "price": 115030
  },
  {
    "rank": 2,
    "symbol": "ETH",
    "price": 4755.48
  },
  {
    "rank": 3,
    "symbol": "XRP",
    "price": 3.03
  },
  {
    "rank": 4,
    "symbol": "USDT",
    "price": 0.99967
  },
  {
    "rank": 5,
    "symbol": "BNB",
    "price": 881.84
  },
  {
    "rank": 6,
    "symbol": "SOL",
    "price": 204.07
  },
  {
    "rank": 7,
    "symbol": "USDC",
    "price": 0.999805
  },
  {
    "rank": 8,
    "symbol": "STETH",
    "price": 4743.72
  },
  {
    "rank": 9,
    "symbol": "DOGE",
    "price": 0.236843
  },
  {
    "rank": 10,
    "symbol": "TRX",
    "price": 0.361189
  },
  {
    "rank": 11,
    "symbol": "ADA",
    "price": 0.912192
  },
  {
    "rank": 12,
    "symbol": "WSTETH",
    "price": 5687.51
  },
  {
    "rank": 13,
    "symbol": "LINK",
    "price": 26.17
  },
  {
    "rank": 14,
    "symbol": "WBETH",
    "price": 5117.09
  },
  {
    "rank": 15,
    "symbol": "HYPE",
    "price": 44.58
  },
  {
    "rank": 16,
    "symbol": "WBTC",
    "price": 115163
  },
  {
    "rank": 17,
    "symbol": "XLM",
    "price": 0.415104
  },
  {
    "rank": 19,
    "symbol": "WEETH",
    "price": 5098.5
  },
  {
    "rank": 18,
    "symbol": "SUI",
    "price": 3.7
  },
  {
    "rank": 20,
    "symbol": "USDE",
    "price": 1.0
  },
  {
    "rank": 21,
    "symbol": "BCH",
    "price": 587.98
  },
  {
    "rank": 22,
    "symbol": "AVAX",
    "price": 25.84
  },
  {
    "rank": 23,
    "symbol": "HBAR",
    "price": 0.251239
  },
  {
    "rank": 24,
    "symbol": "WETH",
    "price": 4755.16
  },
  {
    "rank": 25,
    "symbol": "LTC",
    "price": 120.82
  },
  {
    "rank": 26,
    "symbol": "LEO",
    "price": 9.6
  },
  {
    "rank": 27,
    "symbol": "TON",
    "price": 3.37
  },
  {
    "rank": 28,
    "symbol": "USDS",
    "price": 0.99993
  },
  {
    "rank": 29,
    "symbol": "SHIB",
    "price": 1.324e-05
  },
  {
    "rank": 30,
    "symbol": "UNI",
    "price": 11.34
  },
  {
    "rank": 31,
    "symbol": "BSC-USD",
    "price": 0.999297
  },
  {
    "rank": 33,
    "symbol": "DOT",
    "price": 4.18
  },
  {
    "rank": 32,
    "symbol": "WBT",
    "price": 44.12
  },
  {
    "rank": 34,
    "symbol": "CBBTC",
    "price": 115197
  },
  {
    "rank": 35,
    "symbol": "SUSDE",
    "price": 1.19
  },
  {
    "rank": 36,
    "symbol": "AAVE",
    "price": 353.29
  },
  {
    "rank": 37,
    "symbol": "BGB",
    "price": 4.7
  },
  {
    "rank": 38,
    "symbol": "CRO",
    "price": 0.156762
  },
  {
    "rank": 39,
    "symbol": "ENA",
    "price": 0.747518
  },
  {
    "rank": 40,
    "symbol": "XMR",
    "price": 265.18
  },
  {
    "rank": 41,
    "symbol": "PEPE",
    "price": 1.127e-05
  },
  {
    "rank": 42,
    "symbol": "DAI",
    "price": 0.999955
  },
  {
    "rank": 43,
    "symbol": "OKB",
    "price": 203.24
  },
  {
    "rank": 44,
    "symbol": "MNT",
    "price": 1.23
  },
  {
    "rank": 45,
    "symbol": "ETC",
    "price": 24.01
  },
  {
    "rank": 46,
    "symbol": "TAO",
    "price": 362.71
  },
  {
    "rank": 47,
    "symbol": "NEAR",
    "price": 2.69
  },
  {
    "rank": 48,
    "symbol": "APT",
    "price": 4.73
  },
  {
    "rank": 49,
    "symbol": "ONDO",
    "price": 1.004
  },
  {
    "rank": 50,
    "symbol": "ARB",
    "price": 0.594631
  }
]